tuidb/__init__.py
tuidb/__version__.py
tuidb/__version__.pyi
tuidb/py.typed
tuidb/stopwatch.css
tuidb/stopwatch.py
tuidb-0.1.0.dist-info/LICENSE
tuidb-0.1.0.dist-info/METADATA
tuidb-0.1.0.dist-info/WHEEL
tuidb-0.1.0.dist-info/top_level.txt
tuidb-0.1.0.dist-info/RECORD
